pytregex/__init__.py
pytregex/__main__.py
pytregex/about.py
pytregex/abstract_collins_head_finder.py
pytregex/collins_head_finder.py
pytregex/condition.py
pytregex/exceptions.py
pytregex/glossary.py
pytregex/head_finder.py
pytregex/main.py
pytregex/peekable.py
pytregex/relation.py
pytregex/tree.py
pytregex/tregex.py
pytregex/utils.py
pytregex/international/pennchinese/chinese_head_finder.py
pytregex/ply/__init__.py
pytregex/ply/lex.py
pytregex/ply/yacc.py
pytregex-0.0.2.dist-info/LICENSE
pytregex-0.0.2.dist-info/METADATA
pytregex-0.0.2.dist-info/WHEEL
pytregex-0.0.2.dist-info/entry_points.txt
pytregex-0.0.2.dist-info/top_level.txt
pytregex-0.0.2.dist-info/RECORD
